lifo.v
module lifo #(
    parameter DATA_W = 10,
    parameter LIFO_SIZE = 6 
)(
    input wire write,
    input wire read,
    input wire clock,
    input wire reset,
    input wire [DATA_W-1:0] datain,
    output wire [DATA_W-1:0] dataout,
    output reg val,
    output wire full
);

    localparam COUNT_W = $clog2(LIFO_SIZE+1);
    reg [COUNT_W-1:0] count;

    reg [DATA_W-1:0] elem [LIFO_SIZE-1:0];
    reg [DATA_W-1:0] out_elem;
    assign dataout = out_elem;
    assign full = count == LIFO_SIZE;


    always @(posedge clock) begin : regs
        count <= reset ? 0 :
            write & read ? count :
            write & count < LIFO_SIZE ? count + 1 :
            read & count != 0 ? count - 1 :
            read & count == 0 ? 0 : count;

        val <= read & count != 0 ? 1 : 0;
    end

    always @(posedge clock) begin : read_write
        out_elem <= read & count != 0 ? elem[count - 1] : out_elem; 

        elem[(read ? count - 1 : count)] <= write & full == 0 ? datain : elem[(read ? count - 1 : count)];
    end
endmodule

lifo_testbench.v
module testbench;
    parameter DATA_W = 5;
    parameter LIFO_SIZE = 2;
    reg read;
    reg write;
    reg reset;
    reg clock;
    reg [DATA_W-1:0] datain;
    wire [DATA_W-1:0] dataout;
    wire val;
    wire full;

    lifo #(.DATA_W(DATA_W), .LIFO_SIZE(LIFO_SIZE)) example_lifo(
        .write(write), .read(read), .clock(clock), .reset(reset),
        .datain(datain), .val(val), .full(full), .dataout(dataout)
    );

    always #1 clock = ~clock;

    initial begin
        clock <= 0;
        reset <= 1;
        write <= 0;
        read <= 0;

        #1;

        reset <= 0;
        write <= 1;
        datain <= 5'b10011;

        #2;

        datain <= 5'b11000;

        #2;

        datain <= 5'b10100;
        write <= 0;

        #2;

        read <= 1;

        #6;

        read <= 0;

        #2;

        $finish;
    end

    `include "dump_settings.v"

endmodule

test.vcd
$date
	Sat Mar 15 02:56:00 2025
$end
$version
	Icarus Verilog
$end
$timescale
	1s
$end
$scope module testbench $end
$var wire 1 ! val $end
$var wire 1 " full $end
$var wire 5 # dataout [4:0] $end
$var parameter 32 $ DATA_W $end
$var parameter 32 % LIFO_SIZE $end
$var reg 1 & clock $end
$var reg 5 ' datain [4:0] $end
$var reg 1 ( read $end
$var reg 1 ) reset $end
$var reg 1 * write $end
$scope module example_lifo $end
$var wire 1 & clock $end
$var wire 5 + datain [4:0] $end
$var wire 5 , dataout [4:0] $end
$var wire 1 ( read $end
$var wire 1 ) reset $end
$var wire 1 * write $end
$var wire 1 " full $end
$var parameter 32 - COUNT_W $end
$var parameter 32 . DATA_W $end
$var parameter 32 / LIFO_SIZE $end
$var reg 2 0 count [1:0] $end
$var reg 5 1 out_elem [4:0] $end
$var reg 1 ! val $end
$scope begin read_write $end
$upscope $end
$scope begin regs $end
$upscope $end
$upscope $end
$upscope $end
$enddefinitions $end
$comment Show the parameter values. $end
$dumpall
b10 /
b101 .
b10 -
b10 %
b101 $
$end
#0
$dumpvars
bx 1
bx 0
bx ,
bx +
0*
1)
0(
bx '
0&
bx #
x"
x!
$end
#1
0!
0"
b0 0
b10011 '
b10011 +
1*
0)
1&
#2
0&
#3
b1 0
b11000 '
b11000 +
1&
#4
0&
#5
1"
b10 0
0*
b10100 '
b10100 +
1&
#6
0&
#7
1(
1&
#8
0&
#9
b11000 #
b11000 ,
b11000 1
1!
0"
b1 0
1&
#10
0&
#11
b10011 #
b10011 ,
b10011 1
b0 0
1&
#12
0&
#13
0!
0(
1&
